xcuba/__init__.py
xcuba/tasa_cambio.py
xcuba/vps_costo.py
xcuba-0.0.1.dist-info/licenses/LICENSE
xcuba-0.0.1.dist-info/METADATA
xcuba-0.0.1.dist-info/WHEEL
xcuba-0.0.1.dist-info/top_level.txt
xcuba-0.0.1.dist-info/RECORD
