Metadata-Version: 2.4
Name: xcuba
Version: 0.0.1
Summary: Utilitario para cubanos donde les facilita la vida a los dev
Author-email: KeimaSenpai <KeimaSenpai@proton.me>
License: Creative Commons Attribution-NonCommercial 4.0 International (CC BY-NC 4.0)
Project-URL: Homepage, https://github.com/KeimaSenpai
Project-URL: Documentation, https://github.com/KeimaSenpai
Project-URL: Source, https://github.com/KeimaSenpai
Project-URL: Issues, https://github.com/KeimaSenpai
Project-URL: Community, https://t.me/KeimaSenpai
License-File: LICENSE
Requires-Dist: requests
Requires-Dist: bs4
Dynamic: license-file
